tiny86/circuit/execute/agu.v
`default_nettype none

module agu(
  input [1:0] scale,
  input [31:0] index,
  input [31:0] base,
  input [31:0] disp,

  output [31:0] address
);

assign address = ((1 << scale) * index) + base + disp;

endmodule

tiny86/test/agu.tb.gen.v
// this file was generated by ./codegen/tbgen
// do NOT edit it by hand
module agu_tb();
reg clk, reset;
reg [31:0] current_vec, error_count;
reg [129:0] test_vectors [1023:0];
reg [1:0] scale;
reg [31:0] index;
reg [31:0] base;
reg [31:0] disp;
reg [31:0] exp_address;
wire [31:0] address;
agu dut(
.scale(scale),
.index(index),
.base(base),
.disp(disp),
.address(address)
);
always
  begin
    clk = 1; #5; clk = 0; #5;
  end
initial
  begin
    $dumpfile("agu.tb.vcd");
    $dumpvars(0, agu_tb);
    $readmemb("test/agu.tv", test_vectors);
    current_vec = 0; error_count = 0;
    reset = 1; #10; reset = 0;
  end
always @(posedge clk)
  begin
    #1; { scale, index, base, disp, exp_address } = test_vectors[current_vec];
  end
always @(negedge clk)
  begin
    if (~reset) begin
      if (exp_address === address || exp_address === 32'bx) begin
  $display("TBGEN-PASS agu:%0d address", current_vec);
end else begin
  $display("TBGEN-FAIL agu:%0d expected address to be 0x%h, was 0x%h", current_vec, exp_address, address);
  error_count = error_count + 1;
end

      current_vec = current_vec + 1;

      if (test_vectors[current_vec] === 130'bx) begin
        $display("TBGEN-DONE agu %0d errors=%0d", current_vec, error_count);
        $finish;
      end
    end
  end
endmodule

tiny86/agu.tb.vcd
$date
	Thu Jul 20 15:52:15 2023
$end
$version
	Icarus Verilog
$end
$timescale
	1s
$end
$scope module agu_tb $end
$var wire 32 ! address [31:0] $end
$var reg 32 " base [31:0] $end
$var reg 1 # clk $end
$var reg 32 $ current_vec [31:0] $end
$var reg 32 % disp [31:0] $end
$var reg 32 & error_count [31:0] $end
$var reg 32 ' exp_address [31:0] $end
$var reg 32 ( index [31:0] $end
$var reg 1 ) reset $end
$var reg 2 * scale [1:0] $end
$scope module dut $end
$var wire 32 + base [31:0] $end
$var wire 32 , disp [31:0] $end
$var wire 32 - index [31:0] $end
$var wire 2 . scale [1:0] $end
$var wire 32 / address [31:0] $end
$upscope $end
$upscope $end
$enddefinitions $end
$comment Show the parameter values. $end
$dumpall
$end
#0
$dumpvars
bx /
bx .
bx -
bx ,
bx +
bx *
1)
bx (
bx '
b0 &
bx %
b0 $
1#
bx "
bx !
$end
#5
0#
#10
1#
0)
#11
b10101010101010101010101010101010 !
b10101010101010101010101010101010 /
b0 *
b0 .
b0 (
b0 -
b0 "
b0 +
b10101010101010101010101010101010 %
b10101010101010101010101010101010 ,
b10101010101010101010101010101010 '
#15
b1 $
0#
#20
1#
#21
b10001000100010001000100010001 "
b10001000100010001000100010001 +
b110011001100110011001100110011 !
b110011001100110011001100110011 /
b100010001000100010001000100010 %
b100010001000100010001000100010 ,
b110011001100110011001100110011 '
#25
b10 $
0#
#30
1#
#31
b10101010101010101010101010101010 "
b10101010101010101010101010101010 +
b10101010101010101010101010101010 !
b10101010101010101010101010101010 /
b0 %
b0 ,
b10101010101010101010101010101010 '
#35
b11 $
0#
#40
1#
#41
b11111111 (
b11111111 -
b10101010101010101010101011111111 !
b10101010101010101010101011111111 /
b10101010101010101010101000000000 "
b10101010101010101010101000000000 +
b10101010101010101010101011111111 '
#45
b100 $
0#
#50
1#
#51
b10001000100010001000100000000 "
b10001000100010001000100000000 +
b110011001100110011001111111111 !
b110011001100110011001111111111 /
b100010001000100010001000000000 %
b100010001000100010001000000000 ,
b110011001100110011001111111111 '
#55
b101 $
0#
#60
1#
#61
b1 *
b1 .
b100 (
b100 -
b11111111111111111111111100000000 "
b11111111111111111111111100000000 +
b11111111111111111111111100001000 !
b11111111111111111111111100001000 /
b0 %
b0 ,
b11111111111111111111111100001000 '
#65
b110 $
0#
#70
1#
#71
b10 *
b10 .
b11111111111111111111111100001000 !
b11111111111111111111111100001000 /
b10 (
b10 -
#75
b111 $
0#
#80
1#
#81
b11111111111111111111111100010000 !
b11111111111111111111111100010000 /
b11 *
b11 .
b11111111111111111111111100010000 '
#85
b1000 $
0#
#90
1#
#91
b1 *
b1 .
b0 "
b0 +
b11111111111111111111111100000100 !
b11111111111111111111111100000100 /
b11111111111111111111111100000000 %
b11111111111111111111111100000000 ,
b11111111111111111111111100000100 '
#95
b1001 $
0#
#100
1#
#101
b11111111111111110000000000000000 "
b11111111111111110000000000000000 +
b11111111111111111111111100000100 !
b11111111111111111111111100000100 /
b1111111100000000 %
b1111111100000000 ,
#105
b1010 $
0#
